nrich/__init__.py
nrich/__main__.py
nrich/models.py
nrich/nrich.py
nrich/parse_internetdb.py
nrich-0.1.3.dist-info/LICENSE
nrich-0.1.3.dist-info/METADATA
nrich-0.1.3.dist-info/WHEEL
nrich-0.1.3.dist-info/RECORD
