Metadata-Version: 2.1
Name: nrich
Version: 0.1.3
Summary: Python equivalant of the rust nrich program. Simple async Python program to interact with the Shodan InternetDB API.
License: GPLv3
Author: pimvh
Requires-Python: ==3.11.9
Classifier: License :: Other/Proprietary License
Classifier: Programming Language :: Python :: 3
Requires-Dist: aiohttp (==3.9.5)
